LICENSE.txt
README.md
setup.py
test/test_base_client.py
test/test_beneficiary_api.py
test/test_billing_api.py
test/test_common_apis.py
test/test_exchange_api.py
test/test_payment_api.py
test/test_wallet_api.py
test/test_webhook_api.py
test/test_webhook_signature_util.py
unipayment/__init__.py
unipayment/api_client.py
unipayment/api_exception.py
unipayment/base_client.py
unipayment/beneficiary_api.py
unipayment/billing_api.py
unipayment/common_api.py
unipayment/configuration.py
unipayment/exchange_api.py
unipayment/payment_api.py
unipayment/rest.py
unipayment/token_cache.py
unipayment/unipayment_sdk_exception.py
unipayment/wallet_api.py
unipayment/webhook_api.py
unipayment/webhook_signature_util.py
unipayment.egg-info/PKG-INFO
unipayment.egg-info/SOURCES.txt
unipayment.egg-info/dependency_links.txt
unipayment.egg-info/requires.txt
unipayment.egg-info/top_level.txt
unipayment/models/__init__.py
unipayment/models/accept_quote_response.py
unipayment/models/api_response.py
unipayment/models/bank_account.py
unipayment/models/bank_deposit_address.py
unipayment/models/bank_info.py
unipayment/models/beneficiary.py
unipayment/models/beneficiary_response.py
unipayment/models/buyer_info.py
unipayment/models/check_ipn_response.py
unipayment/models/create_invoice_request.py
unipayment/models/create_invoice_response.py
unipayment/models/create_payment_request.py
unipayment/models/currency.py
unipayment/models/deposit_address.py
unipayment/models/exchange_order.py
unipayment/models/exchange_rate.py
unipayment/models/get_currencies_response.py
unipayment/models/get_deposit_address_response.py
unipayment/models/get_deposit_bank_account_response.py
unipayment/models/get_exchange_rate_response.py
unipayment/models/get_exchange_rates_response.py
unipayment/models/get_invoice_by_id_response.py
unipayment/models/get_payment_fee_response.py
unipayment/models/get_wallet_accounts_response.py
unipayment/models/get_wallet_balances_response.py
unipayment/models/invoice.py
unipayment/models/invoice_detail.py
unipayment/models/payment.py
unipayment/models/payment_fee.py
unipayment/models/payment_method.py
unipayment/models/payment_method_response.py
