Metadata-Version: 2.1
Name: unipayment
Version: 2.0.1
Summary: UniPayment Python SDK
Home-page: https://github.com/UniCryptoLab/UniPaymentClient.Python
License: UNKNOWN
Platform: UNKNOWN
License-File: LICENSE.txt
